selenium_teleport/__init__.py
selenium_teleport/core.py
selenium_teleport-2.0.1.dist-info/licenses/LICENSE
selenium_teleport-2.0.1.dist-info/METADATA
selenium_teleport-2.0.1.dist-info/WHEEL
selenium_teleport-2.0.1.dist-info/top_level.txt
selenium_teleport-2.0.1.dist-info/RECORD
