Metadata-Version: 2.4
Name: selenium-teleport
Version: 2.0.1
Summary: Save and restore browser state (Cookies, LocalStorage, SessionStorage) to instantly skip login screens in Selenium automation.
Author: Dhiraj Das
License: MIT
Project-URL: Homepage, https://github.com/godhiraj-code/selenium-teleport
Project-URL: Documentation, https://github.com/godhiraj-code/selenium-teleport#readme
Project-URL: Repository, https://github.com/godhiraj-code/selenium-teleport
Project-URL: Issues, https://github.com/godhiraj-code/selenium-teleport/issues
Keywords: selenium,automation,testing,browser,cookies,session,state,teleport,login,authentication
Classifier: Development Status :: 4 - Beta
Classifier: Intended Audience :: Developers
Classifier: License :: OSI Approved :: MIT License
Classifier: Operating System :: OS Independent
Classifier: Programming Language :: Python :: 3
Classifier: Programming Language :: Python :: 3.8
Classifier: Programming Language :: Python :: 3.9
Classifier: Programming Language :: Python :: 3.10
Classifier: Programming Language :: Python :: 3.11
Classifier: Programming Language :: Python :: 3.12
Classifier: Topic :: Software Development :: Testing
Classifier: Topic :: Software Development :: Quality Assurance
Requires-Python: >=3.8
License-File: LICENSE
Requires-Dist: selenium>=4.0.0
Provides-Extra: undetected
Requires-Dist: undetected-chromedriver>=3.5.0; extra == "undetected"
Provides-Extra: stealth
Requires-Dist: sb-stealth-wrapper>=0.1.0; extra == "stealth"
Provides-Extra: dev
Requires-Dist: pytest>=7.0.0; extra == "dev"
Requires-Dist: pytest-cov>=4.0.0; extra == "dev"
Requires-Dist: black>=23.0.0; extra == "dev"
Requires-Dist: isort>=5.12.0; extra == "dev"
Requires-Dist: mypy>=1.0.0; extra == "dev"
Requires-Dist: undetected-chromedriver>=3.5.0; extra == "dev"
Requires-Dist: sb-stealth-wrapper>=0.1.0; extra == "dev"
Dynamic: license-file
